src/alu.v
// ============================================================
// ALU MODULE
// ============================================================

module alu #(
    parameter WIDTH     = 32,
    parameter ALU_WIDTH = 4
)(
    input  [WIDTH-1:0]     A,
    input  [WIDTH-1:0]     B,
    input  [ALU_WIDTH-1:0] ALUControl,

    output [WIDTH-1:0]     result,
    output                 carry,
    output                 zero,
    output                 overflow,
    output                 negative,
    output                 divide_by_zero
);

    // ========================================================
    // ADD / SUB
    // ========================================================

    wire [WIDTH-1:0] B_mux;
    wire [WIDTH-1:0] sum;
    wire             cout;

    assign B_mux       = ALUControl[0] ? ~B : B;
    assign {cout, sum} = A + B_mux + ALUControl[0];

    // ========================================================
    // SLT
    // ========================================================

    wire slt_bit;

    assign slt_bit = sum[WIDTH-1] ^ overflow;

    wire [WIDTH-1:0] slt_result;

    assign slt_result = {{WIDTH-1{1'b0}}, slt_bit};

    // ========================================================
    // MULTIPLIER
    // ========================================================

    wire [2*WIDTH-1:0] mul_full;

    booth_multiplier #(
        .N(WIDTH)
    ) u_mul (
        .multiplicand(A),
        .multiplier(B),
        .product(mul_full)
    );

    wire [WIDTH-1:0] mul_result_low;
    wire [WIDTH-1:0] mul_result_high;

    assign mul_result_low  = mul_full[WIDTH-1:0];
    assign mul_result_high = mul_full[2*WIDTH-1:WIDTH];

    // ========================================================
    // DIVIDER
    // ========================================================

    wire [WIDTH-1:0] div_quotient;
    wire [WIDTH-1:0] div_remainder;

    non_restoring_divider_comb #(
        .WIDTH(WIDTH)
    ) u_div (
        .dividend(A),
        .divisor(B),
        .signed_mode(1'b1),
        .quotient(div_quotient),
        .remainder(div_remainder),
        .divide_by_zero(divide_by_zero)
    );

    // ========================================================
    // RESULT MUX
    // ========================================================

    reg [WIDTH-1:0] mux_out;

    always @(*) begin
        case (ALUControl)

            4'b0000: mux_out = sum;              // ADD
            4'b0001: mux_out = sum;              // SUB

            4'b0010: mux_out = A & B;            // AND
            4'b0011: mux_out = A | B;            // OR
            4'b0100: mux_out = A ^ B;            // XOR

            4'b0101: mux_out = mul_result_low;   // MUL LOW
            4'b0110: mux_out = mul_result_high;  // MUL HIGH

            4'b0111: mux_out = div_quotient;     // DIV
            4'b1000: mux_out = div_remainder;    // REM

            4'b1001: mux_out = slt_result;       // SLT

            default: mux_out = {WIDTH{1'b0}};

        endcase
    end

    assign result = mux_out;

    // ========================================================
    // FLAGS
    // ========================================================

    assign zero     = ~|result;
    assign carry    = cout & ~ALUControl[1];
    assign negative = result[WIDTH-1];

    assign overflow =
        ~ALUControl[2] &
        ~ALUControl[1] &
        (sum[WIDTH-1] ^ A[WIDTH-1]) &
        ~(ALUControl[0] ^ A[WIDTH-1] ^ B[WIDTH-1]);

endmodule


// ============================================================
// BOOTH MULTIPLIER (CORRECTED)
// ============================================================

module booth_multiplier #(
    parameter N = 32
)(
    input  signed [N-1:0]       multiplicand,
    input  signed [N-1:0]       multiplier,
    output reg signed [2*N-1:0] product
);

    integer i;

    reg signed [N:0]   A;      // N+1 bits (sign-extended accumulator)
    reg        [N-1:0] Q;      // N bits   (running multiplier)
    reg signed [N-1:0] M;      // N bits   (multiplicand)
    reg                Q_1;    // 1 bit    (previous LSB of Q)

    reg signed [2*N+1:0] temp; // 2N+2 bits for {A(N+1), Q(N), Q_1(1)}

    always @(*) begin
        A   = {{1{multiplicand[N-1]}}, {N{1'b0}}};  // sign-extended zero
        Q   = multiplier;
        M   = multiplicand;
        Q_1 = 1'b0;

        for (i = 0; i < N; i = i + 1) begin

            // Step 1: add/subtract based on {Q[0], Q_1}
            case ({Q[0], Q_1})
                2'b01: A = A + {{1{M[N-1]}}, M};   // sign-extend M to N+1 bits
                2'b10: A = A - {{1{M[N-1]}}, M};
                default: ;
            endcase

            // Step 2: arithmetic right shift of {A, Q, Q_1} as one unit
            // Total width = (N+1) + N + 1 = 2N+2
            temp = $signed({A, Q, Q_1}) >>> 1;

            //  temp[2N+1:N+1] = new A  (N+1 bits)
            //  temp[N:1]      = new Q  (N bits)
            //  temp[0]        = new Q_1 (1 bit)
            A   = temp[2*N+1 : N+1];
            Q   = temp[N     : 1  ];
            Q_1 = temp[0];

        end

        product = {A[N-1:0], Q};  // drop the extra sign bit of A
    end

endmodule


// ============================================================
// NON-RESTORING DIVIDER
// ============================================================

module non_restoring_divider_comb #(
    parameter WIDTH = 32
)(
    input  wire [WIDTH-1:0] dividend,
    input  wire [WIDTH-1:0] divisor,
    input  wire             signed_mode,

    output reg  [WIDTH-1:0] quotient,
    output reg  [WIDTH-1:0] remainder,
    output reg              divide_by_zero
);

    integer i;

    reg [WIDTH:0]   A;
    reg [WIDTH-1:0] Q;
    reg [WIDTH-1:0] M;

    reg [WIDTH-1:0] dividend_abs;
    reg [WIDTH-1:0] divisor_abs;

    reg dividend_sign;
    reg divisor_sign;

    reg quotient_sign;
    reg remainder_sign;

    reg [WIDTH:0] tempA;

    always @(*) begin

        quotient       = 0;
        remainder      = 0;
        divide_by_zero = 0;

        if (divisor == 0) begin

            divide_by_zero = 1'b1;

        end
        else begin

            dividend_sign = signed_mode & dividend[WIDTH-1];
            divisor_sign  = signed_mode & divisor[WIDTH-1];

            dividend_abs =
                dividend_sign ? (~dividend + 1'b1) : dividend;

            divisor_abs =
                divisor_sign ? (~divisor + 1'b1) : divisor;

            quotient_sign  = dividend_sign ^ divisor_sign;
            remainder_sign = dividend_sign;

            A = 0;
            Q = dividend_abs;
            M = divisor_abs;

            for (i = 0; i < WIDTH; i = i + 1) begin

                A = {A[WIDTH-1:0], Q[WIDTH-1]};
                Q = {Q[WIDTH-2:0], 1'b0};

                if (A[WIDTH] == 0)
                    tempA = A - {1'b0, M};
                else
                    tempA = A + {1'b0, M};

                Q[0] = (tempA[WIDTH] == 0);

                A = tempA;

            end

            // Final correction
            if (A[WIDTH] == 1)
                A = A + {1'b0, M};

            quotient =
                quotient_sign ? (~Q + 1'b1) : Q;

            remainder =
                remainder_sign ? (~A[WIDTH-1:0] + 1'b1)
                               : A[WIDTH-1:0];

        end
    end

endmodule

src/alu_tb.v
module alu_tb;

    // ─────────────────────────────────────────────────────────
    // Parameters
    // ─────────────────────────────────────────────────────────
    parameter WIDTH     = 32;
    parameter ALU_WIDTH = 4;

    // ─────────────────────────────────────────────────────────
    // DUT Inputs
    // ─────────────────────────────────────────────────────────
    reg  [WIDTH-1:0]     A, B;
    reg  [ALU_WIDTH-1:0] ALUControl;

    // ─────────────────────────────────────────────────────────
    // DUT Outputs
    // ─────────────────────────────────────────────────────────
    wire [WIDTH-1:0] result;
    wire carry;
    wire zero;
    wire overflow;
    wire negative;
    wire divide_by_zero;

    // ─────────────────────────────────────────────────────────
    // Signed aliases for GTKWave
    // ─────────────────────────────────────────────────────────
    wire signed [WIDTH-1:0] A_signed;
    wire signed [WIDTH-1:0] B_signed;
    wire signed [WIDTH-1:0] result_signed;

    assign A_signed      = A;
    assign B_signed      = B;
    assign result_signed = result;

    // ─────────────────────────────────────────────────────────
    // DUT
    // ─────────────────────────────────────────────────────────
    alu #(
        .WIDTH(WIDTH),
        .ALU_WIDTH(ALU_WIDTH)
    ) dut (
        .A(A),
        .B(B),
        .ALUControl(ALUControl),
        .result(result),
        .carry(carry),
        .zero(zero),
        .overflow(overflow),
        .negative(negative),
        .divide_by_zero(divide_by_zero)
    );

    // ─────────────────────────────────────────────────────────
    // VCD Dump
    // ─────────────────────────────────────────────────────────
    initial begin
        $dumpfile("alu_wave.vcd");
        $dumpvars(0, alu_tb);

        $display("========================================");
        $display(" GTKWave:");
        $display(" Right click signal ->");
        $display(" Data Format -> Signed Decimal");
        $display("========================================");
    end

    // ─────────────────────────────────────────────────────────
    // Counters
    // ─────────────────────────────────────────────────────────
    integer pass_count;
    integer fail_count;

    // ─────────────────────────────────────────────────────────
    // Generic Check Task
    // ─────────────────────────────────────────────────────────
    task check;
        input [WIDTH-1:0] exp_result;
        input             exp_zero;
        input             exp_negative;
        input             exp_overflow;
        input [127:0]     test_name;

        begin
            #5;

            if ((result    !== exp_result)   ||
                (zero      !== exp_zero)     ||
                (negative  !== exp_negative) ||
                (overflow  !== exp_overflow)) begin

                $display("FAIL [%0s]", test_name);
                $display("  A        = %0d", $signed(A));
                $display("  B        = %0d", $signed(B));
                $display("  CTRL     = %b", ALUControl);

                $display("  RESULT   = %0d (exp %0d)",
                         $signed(result),
                         $signed(exp_result));

                $display("  ZERO     = %b (exp %b)",
                         zero, exp_zero);

                $display("  NEGATIVE = %b (exp %b)",
                         negative, exp_negative);

                $display("  OVERFLOW = %b (exp %b)",
                         overflow, exp_overflow);

                fail_count = fail_count + 1;

            end else begin

                $display("PASS [%0s] RESULT=%0d",
                         test_name,
                         $signed(result));

                pass_count = pass_count + 1;
            end

            #5;
        end
    endtask

    // ─────────────────────────────────────────────────────────
    // Division Check Task
    // ─────────────────────────────────────────────────────────
    task check_div;
        input [WIDTH-1:0] exp_result;
        input             exp_dbz;
        input [127:0]     test_name;

        begin
            #5;

            if ((result !== exp_result) ||
                (divide_by_zero !== exp_dbz)) begin

                $display("FAIL [%0s]", test_name);

                $display("  A      = %0d", $signed(A));
                $display("  B      = %0d", $signed(B));
                $display("  CTRL   = %b", ALUControl);

                $display("  RESULT = %0d (exp %0d)",
                         $signed(result),
                         $signed(exp_result));

                $display("  DBZ    = %b (exp %b)",
                         divide_by_zero,
                         exp_dbz);

                fail_count = fail_count + 1;

            end else begin

                $display("PASS [%0s] RESULT=%0d",
                         test_name,
                         $signed(result));

                pass_count = pass_count + 1;
            end

            #5;
        end
    endtask

    // ─────────────────────────────────────────────────────────
    // Test Stimulus
    // ─────────────────────────────────────────────────────────
    initial begin

        pass_count = 0;
        fail_count = 0;

        $display("\n========================================");
        $display(" ALU TESTBENCH");
        $display(" WIDTH = %0d", WIDTH);
        $display("========================================");

        // ====================================================
        // ADD
        // ====================================================
        $display("\n--- ADD ---");

        A = 32'd15;
        B = 32'd10;
        ALUControl = 4'b0000;
        check(32'd25, 0, 0, 0, "ADD basic");

        A = 32'd0;
        B = 32'd0;
        ALUControl = 4'b0000;
        check(32'd0, 1, 0, 0, "ADD zero");

        A = 32'h7FFF_FFFF;
        B = 32'd1;
        ALUControl = 4'b0000;
        check(32'h8000_0000, 0, 1, 1, "ADD overflow");

        // ====================================================
        // SUB
        // ====================================================
        $display("\n--- SUB ---");

        A = 32'd20;
        B = 32'd5;
        ALUControl = 4'b0001;
        check(32'd15, 0, 0, 0, "SUB basic");

        A = 32'd5;
        B = 32'd5;
        ALUControl = 4'b0001;
        check(32'd0, 1, 0, 0, "SUB zero");

        A = 32'd3;
        B = 32'd10;
        ALUControl = 4'b0001;
        check(32'hFFFF_FFF9, 0, 1, 0, "SUB negative");

        A = 32'h8000_0000;
        B = 32'd1;
        ALUControl = 4'b0001;
        check(32'h7FFF_FFFF, 0, 0, 1, "SUB overflow");

        // ====================================================
        // AND
        // ====================================================
        $display("\n--- AND ---");

        A = 32'hFF00_FF00;
        B = 32'hF0F0_F0F0;
        ALUControl = 4'b0010;
        check(32'hF000_F000, 0, 1, 0, "AND pattern");

        A = 32'hAAAA_AAAA;
        B = 32'h5555_5555;
        ALUControl = 4'b0010;
        check(32'h0000_0000, 1, 0, 0, "AND zero");

        // ====================================================
        // OR
        // ====================================================
        $display("\n--- OR ---");

        A = 32'hFF00_0000;
        B = 32'h00FF_0000;
        ALUControl = 4'b0011;
        check(32'hFFFF_0000, 0, 1, 0, "OR combine");

        A = 32'h0;
        B = 32'h0;
        ALUControl = 4'b0011;
        check(32'h0, 1, 0, 0, "OR zero");

        // ====================================================
        // XOR
        // ====================================================
        $display("\n--- XOR ---");

        A = 32'hFFFF_FFFF;
        B = 32'hFFFF_FFFF;
        ALUControl = 4'b0100;
        check(32'h0000_0000, 1, 0, 0, "XOR same");

        A = 32'hAAAA_AAAA;
        B = 32'h5555_5555;
        ALUControl = 4'b0100;
        check(32'hFFFF_FFFF, 0, 1, 0, "XOR alternating");

        // ====================================================
        // MUL LOW
        // ====================================================
        $display("\n--- MUL LOW ---");

        A = 32'd6;
        B = 32'd7;
        ALUControl = 4'b0101;
        check(32'd42, 0, 0, 0, "MUL 6x7");

        A = 32'd0;
        B = 32'd999;
        ALUControl = 4'b0101;
        check(32'd0, 1, 0, 0, "MUL by zero");

        A = -32'd3;
        B = 32'd4;
        ALUControl = 4'b0101;
        check(-32'd12, 0, 1, 0, "MUL neg*pos");

        A = -32'd5;
        B = -32'd5;
        ALUControl = 4'b0101;
        check(32'd25, 0, 0, 0, "MUL neg*neg");

        // ====================================================
        // DIV QUOTIENT
        // ====================================================
        $display("\n--- DIV QUOTIENT ---");

        A = 32'd20;
        B = 32'd4;
        ALUControl = 4'b0111;
        check_div(32'd5, 0, "DIV 20/4");

        A = 32'd7;
        B = 32'd2;
        ALUControl = 4'b0111;
        check_div(32'd3, 0, "DIV 7/2");

        A = -32'd20;
        B = 32'd4;
        ALUControl = 4'b0111;
        check_div(-32'd5, 0, "DIV -20/4");

        A = 32'd99;
        B = 32'd0;
        ALUControl = 4'b0111;
        check_div(32'd0, 1, "DIV by zero");

        // ====================================================
        // REMAINDER
        // ====================================================
        $display("\n--- REMAINDER ---");

        A = 32'd20;
        B = 32'd6;
        ALUControl = 4'b1000;
        check(32'd2, 0, 0, 0, "REM 20%6");

        A = -32'd20;
        B = 32'd6;
        ALUControl = 4'b1000;
        check(-32'd2, 0, 1, 0, "REM -20%6");

        // ====================================================
        // SLT
        // ====================================================
        $display("\n--- SLT ---");

        A = 32'd3;
        B = 32'd10;
        ALUControl = 4'b1001;
        check(32'd1, 0, 0, 0, "SLT 3<10");

        A = 32'd10;
        B = 32'd3;
        ALUControl = 4'b1001;
        check(32'd0, 1, 0, 0, "SLT 10>=3");

        A = 32'd5;
        B = 32'd5;
        ALUControl = 4'b1001;
        check(32'd0, 1, 0, 0, "SLT equal");

        A = -32'd1;
        B = 32'd0;
        ALUControl = 4'b1001;
        check(32'd1, 0, 0, 0, "SLT -1<0");

        A = 32'h8000_0000;
        B = 32'd0;
        ALUControl = 4'b1001;
        check(32'd1, 0, 0, 0, "SLT INT_MIN");

        // ====================================================
        // Summary
        // ====================================================
        $display("\n========================================");
        $display(" TEST SUMMARY");
        $display(" PASSED = %0d", pass_count);
        $display(" FAILED = %0d", fail_count);
        $display("========================================");

        #10;
        $finish;
    end

endmodule

src/alu_wave.vcd
$date
	Mon May 25 07:27:21 2026
$end
$version
	Icarus Verilog
$end
$timescale
	1s
$end
$scope module alu_tb $end
$var wire 32 ! A_signed [31:0] $end
$var wire 32 " B_signed [31:0] $end
$var wire 32 # result_signed [31:0] $end
$var wire 1 $ zero $end
$var wire 32 % result [31:0] $end
$var wire 1 & overflow $end
$var wire 1 ' negative $end
$var wire 1 ( divide_by_zero $end
$var wire 1 ) carry $end
$var parameter 32 * ALU_WIDTH $end
$var parameter 32 + WIDTH $end
$var reg 32 , A [31:0] $end
$var reg 4 - ALUControl [3:0] $end
$var reg 32 . B [31:0] $end
$var integer 32 / fail_count [31:0] $end
$var integer 32 0 pass_count [31:0] $end
$scope module dut $end
$var wire 32 1 A [31:0] $end
$var wire 4 2 ALUControl [3:0] $end
$var wire 32 3 B [31:0] $end
$var wire 1 ) carry $end
$var wire 1 & overflow $end
$var wire 32 4 result [31:0] $end
$var wire 1 5 slt_bit $end
$var wire 1 $ zero $end
$var wire 32 6 sum [31:0] $end
$var wire 32 7 slt_result [31:0] $end
$var wire 1 ' negative $end
$var wire 32 8 mul_result_low [31:0] $end
$var wire 32 9 mul_result_high [31:0] $end
$var wire 64 : mul_full [63:0] $end
$var wire 1 ( divide_by_zero $end
$var wire 32 ; div_remainder [31:0] $end
$var wire 32 < div_quotient [31:0] $end
$var wire 1 = cout $end
$var wire 32 > B_mux [31:0] $end
$var parameter 32 ? ALU_WIDTH $end
$var parameter 32 @ WIDTH $end
$var reg 32 A mux_out [31:0] $end
$scope module u_div $end
$var wire 32 B dividend [31:0] $end
$var wire 32 C divisor [31:0] $end
$var wire 1 D signed_mode $end
$var parameter 32 E WIDTH $end
$var reg 33 F A [32:0] $end
$var reg 32 G M [31:0] $end
$var reg 32 H Q [31:0] $end
$var reg 1 ( divide_by_zero $end
$var reg 32 I dividend_abs [31:0] $end
$var reg 1 J dividend_sign $end
$var reg 32 K divisor_abs [31:0] $end
$var reg 1 L divisor_sign $end
$var reg 32 M quotient [31:0] $end
$var reg 1 N quotient_sign $end
$var reg 32 O remainder [31:0] $end
$var reg 1 P remainder_sign $end
$var reg 33 Q tempA [32:0] $end
$var integer 32 R i [31:0] $end
$upscope $end
$scope module u_mul $end
$var wire 32 S multiplicand [31:0] $end
$var wire 32 T multiplier [31:0] $end
$var parameter 32 U N $end
$var reg 33 V A [32:0] $end
$var reg 32 W M [31:0] $end
$var reg 32 X Q [31:0] $end
$var reg 1 Y Q_1 $end
$var reg 64 Z product [63:0] $end
$var reg 66 [ temp [65:0] $end
$var integer 32 \ i [31:0] $end
$upscope $end
$upscope $end
$scope task check $end
$var reg 1 ] exp_negative $end
$var reg 1 ^ exp_overflow $end
$var reg 32 _ exp_result [31:0] $end
$var reg 1 ` exp_zero $end
$var reg 128 a test_name [127:0] $end
$upscope $end
$scope task check_div $end
$var reg 1 b exp_dbz $end
$var reg 32 c exp_result [31:0] $end
$var reg 128 d test_name [127:0] $end
$upscope $end
$upscope $end
$enddefinitions $end
$comment Show the parameter values. $end
$dumpall
b100000 U
b100000 E
b100000 @
b100 ?
b100000 +
b100 *
$end
#0
$dumpvars
bx d
bx c
xb
b10000010100010001000100001000000110001001100001011100110110100101100011 a
0`
b11001 _
0^
0]
b100000 \
b100101100 [
b10010110 Z
0Y
b10010110 X
b1111 W
b0 V
b1010 T
b1111 S
b100000 R
b101 Q
0P
b101 O
0N
b1 M
0L
b1010 K
0J
b1111 I
b1 H
b1010 G
b101 F
1D
b1010 C
b1111 B
b11001 A
b1010 >
0=
b1 <
b101 ;
b10010110 :
b0 9
b10010110 8
b0 7
b11001 6
05
b11001 4
b1010 3
b0 2
b1111 1
b0 0
b0 /
b1010 .
b0 -
b1111 ,
0)
0(
0'
0&
b11001 %
0$
b11001 #
b1010 "
b1111 !
$end
#5
b1 0
#10
1$
b0 #
b0 %
b0 4
b0 A
b0 8
b0 >
b0 6
1(
b0 ;
b0 O
b0 <
b0 M
b0 :
b0 Z
b0 [
b100000 \
b0 W
b0 X
b100000101000100010001000010000001111010011001010111001001101111 a
1`
b0 _
b0 "
b0 .
b0 3
b0 C
b0 T
b0 !
b0 ,
b0 1
b0 B
b0 S
#15
b10 0
#20
1&
b0 7
05
1'
0$
b10000000000000000000000000000000 #
b10000000000000000000000000000000 %
b10000000000000000000000000000000 4
b10000000000000000000000000000000 A
b1111111111111111111111111111111 8
b1 >
b10000000000000000000000000000000 6
b1111111111111111111111111111111 <
b1111111111111111111111111111111 M
b0 Q
b100000 R
b1 G
b1111111111111111111111111111111 H
b0 F
b1 K
b1111111111111111111111111111111 I
0(
b1111111111111111111111111111111 :
b1111111111111111111111111111111 Z
0Y
b11111111111111111111111111111110 [
b0 V
b100000 \
b1111111111111111111111111111111 W
b1111111111111111111111111111111 X
b10000010100010001000100001000000110111101110110011001010111001001100110011011000110111101110111 a
1^
1]
0`
b10000000000000000000000000000000 _
b1 "
b1 .
b1 3
b1 C
b1 T
b1111111111111111111111111111111 !
b1111111111111111111111111111111 ,
b1111111111111111111111111111111 1
b1111111111111111111111111111111 B
b1111111111111111111111111111111 S
#25
b11 0
#30
0&
1)
1=
b0 7
05
0'
b1111 #
b1111 %
b1111 4
b1111 A
b1100100 8
b11111111111111111111111111111010 >
b1111 6
b0 F
b111111111111111111111111111111011 Q
b100000 R
b101 G
b100 H
b101 K
b10100 I
b100 <
b100 M
b1100100 :
b1100100 Z
0Y
b11001000 [
b0 V
b100000 \
b10100 W
b1100100 X
b10100110101010101000010001000000110001001100001011100110110100101100011 a
0^
0]
b1111 _
b1 -
b1 2
b101 "
b101 .
b101 3
b101 C
b101 T
b10100 !
b10100 ,
b10100 1
b10100 B
b10100 S
#35
b100 0
#40
1$
b0 #
b0 %
b0 4
b0 A
b11001 8
b0 6
b0 Q
b0 F
b100000 R
b1 H
b101 I
b1 <
b1 M
b11001 :
b11001 Z
0Y
b110010 [
b0 V
b100000 \
b101 W
b11001 X
b101001101010101010000100010000001111010011001010111001001101111 a
1`
b0 _
b101 !
b101 ,
b101 1
b101 B
b101 S
#45
b101 0
#50
b1 7
15
1'
b11111111111111111111111111110101 >
0)
0$
b11111111111111111111111111111001 #
b11111111111111111111111111111001 %
b11111111111111111111111111111001 4
b11111111111111111111111111111001 A
b11110 8
b11111111111111111111111111111001 6
0=
b11 ;
b11 O
b11 F
b111111111111111111111111111111001 Q
b100000 R
b1010 G
b0 H
b1010 K
b11 I
b0 <
b0 M
b11110 :
b11110 Z
0Y
b0 V
b111100 [
b100000 \
b11 W
b11110 X
b10100110101010101000010001000000110111001100101011001110110000101110100011010010111011001100101 a
1]
0`
b11111111111111111111111111111001 _
b1010 "
b1010 .
b1010 3
b1010 C
b1010 T
b11 !
b11 ,
b11 1
b11 B
b11 S
#55
b110 0
#60
1&
b1 7
15
0'
b11111111111111111111111111111110 >
1)
b1111111111111111111111111111111 #
b1111111111111111111111111111111 %
b1111111111111111111111111111111 4
b1111111111111111111111111111111 A
b11111111111111111111111111111110 9
b10000000000000000000000000000000 8
b1111111111111111111111111111111 6
1=
b10000000000000000000000000000000 <
b10000000000000000000000000000000 M
b111111111111111111111111111111111 Q
b100000 R
b1 G
b10000000000000000000000000000000 H
b0 F
1P
1N
b1 K
b10000000000000000000000000000000 I
1J
b0 ;
b0 O
b1111111111111111111111111111111010000000000000000000000000000000 :
b1111111111111111111111111111111010000000000000000000000000000000 Z
0Y
b111111111111111111111111111111110100000000000000000000000000000000 [
b100000 \
b10000000000000000000000000000000 W
b10000000000000000000000000000000 X
b111111111111111111111111111111110 V
b10100110101010101000010001000000110111101110110011001010111001001100110011011000110111101110111 a
1^
0]
b1111111111111111111111111111111 _
b1 "
b1 .
b1 3
b1 C
b1 T
b10000000000000000000000000000000 !
b10000000000000000000000000000000 ,
b10000000000000000000000000000000 1
b10000000000000000000000000000000 B
b10000000000000000000000000000000 S
#65
b111 0
#70
0&
0)
b1 7
15
b11110000111100001111000011110000 >
b11110000000000001110 9
b1111111111110001000000000000 8
1'
b11101111111100011110111111110000 6
b11111111000000001111111100000000 ;
b11111111000000001111111100000000 O
b111111110000000100000000 F
b111110001111011111111000111110000 Q
b100000 R
b1111000011110000111100010000 G
b0 H
0N
b1111000011110000111100010000 K
b111111110000000100000000 I
1L
b0 <
b0 M
b1111000000000000111000001111111111110001000000000000 :
b1111000000000000111000001111111111110001000000000000 Z
1Y
b11110000000000001110000011111111111100010000000000001 [
b100000 \
b11111111000000001111111100000000 W
b1111111111110001000000000000 X
b11110000000000001110 V
b11110000000000001111000000000000 #
b11110000000000001111000000000000 %
b11110000000000001111000000000000 4
b11110000000000001111000000000000 A
b100000101001110010001000010000001110000011000010111010001110100011001010111001001101110 a
0^
1]
b11110000000000001111000000000000 _
b10 -
b10 2
b11110000111100001111000011110000 "
b11110000111100001111000011110000 .
b11110000111100001111000011110000 3
b11110000111100001111000011110000 C
b11110000111100001111000011110000 T
b11111111000000001111111100000000 !
b11111111000000001111111100000000 ,
b11111111000000001111111100000000 1
b11111111000000001111111100000000 B
b11111111000000001111111100000000 S
#75
b1000 0
#80
0=
b11100011100011100011100011100010 9
b1110001110001110001110001110010 8
0'
b1010101010101010101010101010101 >
b11111111111111111111111111111111 6
b11111111111111111111111111111111 <
b11111111111111111111111111111111 M
b1 Q
b100000 R
b1010101010101010101010101010101 G
b1 H
b1 F
1N
b1010101010101010101010101010101 K
b1010101010101010101010101010110 I
0L
b11111111111111111111111111111111 ;
b11111111111111111111111111111111 O
b1110001110001110001110001110001001110001110001110001110001110010 :
b1110001110001110001110001110001001110001110001110001110001110010 Z
b111100011100011100011100011100010011100011100011100011100011100100 [
b100000 \
0Y
b10101010101010101010101010101010 W
b1110001110001110001110001110010 X
b111100011100011100011100011100010 V
1$
b0 #
b0 %
b0 4
b0 A
b100000101001110010001000010000001111010011001010111001001101111 a
0]
1`
b0 _
b1010101010101010101010101010101 "
b1010101010101010101010101010101 .
b1010101010101010101010101010101 3
b1010101010101010101010101010101 C
b1010101010101010101010101010101 T
b10101010101010101010101010101010 !
b10101010101010101010101010101010 ,
b10101010101010101010101010101010 1
b10101010101010101010101010101010 B
b10101010101010101010101010101010 S
#85
b1001 0
#90
b1 7
15
b11111111111111110000000011111111 9
b0 8
1'
b11111111000000001111111111111111 >
b11111110000000010000000000000000 6
1=
b10000000000000000 Q
b100000 R
b111111110000000000000000 G
b1 H
b10000000000000000 F
b111111110000000000000000 K
b1000000000000000000000000 I
b11111111111111110000000000000000 ;
b11111111111111110000000000000000 O
b11111111111111111111111111111111 <
b11111111111111111111111111111111 M
b1111111111111111000000001111111100000000000000000000000000000000 :
b1111111111111111000000001111111100000000000000000000000000000000 Z
0Y
b111111111111111110000000011111111000000000000000000000000000000000 [
b100000 \
b11111111000000000000000000000000 W
b0 X
b111111111111111110000000011111111 V
0$
b11111111111111110000000000000000 #
b11111111111111110000000000000000 %
b11111111111111110000000000000000 4
b11111111111111110000000000000000 A
b1001111010100100010000001100011011011110110110101100010011010010110111001100101 a
1]
0`
b11111111111111110000000000000000 _
b11 -
b11 2
b111111110000000000000000 "
b111111110000000000000000 .
b111111110000000000000000 3
b111111110000000000000000 C
b111111110000000000000000 T
b11111111000000000000000000000000 !
b11111111000000000000000000000000 ,
b11111111000000000000000000000000 1
b11111111000000000000000000000000 B
b11111111000000000000000000000000 S
#95
b1010 0
#100
b0 7
05
b11111111111111111111111111111111 >
b0 9
0'
b0 6
1=
1(
b0 ;
b0 O
b0 <
b0 M
b0 :
b0 Z
b0 [
b100000 \
b0 W
b0 V
1$
b0 #
b0 %
b0 4
b0 A
b1001111010100100010000001111010011001010111001001101111 a
0]
1`
b0 _
b0 "
b0 .
b0 3
b0 C
b0 T
b0 !
b0 ,
b0 1
b0 B
b0 S
#105
b1011 0
#110
1)
b1 7
15
b11111111111111111111111111111111 9
b1 8
b11111111111111111111111111111110 6
b1 <
b1 M
b0 Q
b1 H
b100000 R
b1 G
b0 F
0N
b1 K
b1 I
1L
0(
b1111111111111111111111111111111100000000000000000000000000000001 :
b1111111111111111111111111111111100000000000000000000000000000001 Z
1Y
b111111111111111111111111111111111000000000000000000000000000000011 [
b100000 \
b11111111111111111111111111111111 W
b1 X
b111111111111111111111111111111111 V
b101100001001111010100100010000001110011011000010110110101100101 a
b100 -
b100 2
b11111111111111111111111111111111 "
b11111111111111111111111111111111 .
b11111111111111111111111111111111 3
b11111111111111111111111111111111 C
b11111111111111111111111111111111 T
b11111111111111111111111111111111 !
b11111111111111111111111111111111 ,
b11111111111111111111111111111111 1
b11111111111111111111111111111111 B
b11111111111111111111111111111111 S
#115
b1100 0
#120
0)
0=
b11100011100011100011100011100010 9
b1110001110001110001110001110010 8
1'
b1010101010101010101010101010101 >
b11111111111111111111111111111111 6
b11111111111111111111111111111111 ;
b11111111111111111111111111111111 O
b1 F
b1 Q
b100000 R
b1010101010101010101010101010101 G
b1 H
1N
b1010101010101010101010101010101 K
b1010101010101010101010101010110 I
0L
b11111111111111111111111111111111 <
b11111111111111111111111111111111 M
b1110001110001110001110001110001001110001110001110001110001110010 :
b1110001110001110001110001110001001110001110001110001110001110010 Z
b111100011100011100011100011100010011100011100011100011100011100100 [
b100000 \
0Y
b10101010101010101010101010101010 W
b1110001110001110001110001110010 X
b111100011100011100011100011100010 V
0$
b11111111111111111111111111111111 #
b11111111111111111111111111111111 %
b11111111111111111111111111111111 4
b11111111111111111111111111111111 A
b10110000100111101010010001000000110000101101100011101000110010101110010011011100110000101110100011010010110111001100111 a
1]
0`
b11111111111111111111111111111111 _
b1010101010101010101010101010101 "
b1010101010101010101010101010101 .
b1010101010101010101010101010101 3
b1010101010101010101010101010101 C
b1010101010101010101010101010101 T
b10101010101010101010101010101010 !
b10101010101010101010101010101010 ,
b10101010101010101010101010101010 1
b10101010101010101010101010101010 B
b10101010101010101010101010101010 S
#125
b1101 0
#130
b1 7
15
b0 9
b101010 8
0'
b11111111111111111111111111111000 >
b11111111111111111111111111111111 6
b111111111111111111111111111111111 Q
b100000 R
b111 G
b0 H
b110 F
0P
0N
b111 K
b110 I
0J
b110 ;
b110 O
b0 <
b0 M
b101010 :
b101010 Z
0Y
b1010100 [
b100000 \
b110 W
b101010 X
b0 V
b101010 #
b101010 %
b101010 4
b101010 A
b1001101010101010100110000100000001101100111100000110111 a
0]
b101010 _
b101 -
b101 2
b111 "
b111 .
b111 3
b111 C
b111 T
b110 !
b110 ,
b110 1
b110 B
b110 S
#135
b1110 0
#140
b11111111111111111111110000011000 >
1$
b0 #
b0 %
b0 4
b0 A
b0 8
b11111111111111111111110000011001 6
b111111111111111111111110000011001 Q
b100000 R
b1111100111 G
b0 F
b1111100111 K
b0 I
b0 ;
b0 O
b0 :
b0 Z
0Y
b0 [
b100000 \
b0 W
b0 X
b100110101010101010011000010000001100010011110010010000001111010011001010111001001101111 a
1`
b0 _
b1111100111 "
b1111100111 .
b1111100111 3
b1111100111 C
b1111100111 T
b0 !
b0 ,
b0 1
b0 B
b0 S
#145
b1111 0
